ptda/__init__.py
ptda/core.py
ptda/general.py
PtDa-0.1.8.dist-info/LICENSE
PtDa-0.1.8.dist-info/METADATA
PtDa-0.1.8.dist-info/WHEEL
PtDa-0.1.8.dist-info/top_level.txt
PtDa-0.1.8.dist-info/RECORD
