Metadata-Version: 2.1
Name: PtDa
Version: 0.1.8
Summary: Python package for data analytics.
Home-page: https://github.com/luckyp71/ptda
Author: Lucky Pratama
Author-email: lucky.pratama71@yahoo.com
License: BSD 2-clause
Platform: UNKNOWN
Classifier: Intended Audience :: Science/Research
Classifier: License :: OSI Approved :: BSD License
Classifier: Programming Language :: Python :: 3
Classifier: Programming Language :: Python :: 3.4
Classifier: Programming Language :: Python :: 3.5
Requires-Dist: pandas
Requires-Dist: numpy
Requires-Dist: scipy
